{"stats":{"minecraft:custom":{"minecraft:interact_with_furnace":65,"minecraft:mob_kills":8,"minecraft:interact_with_crafting_table":19,"minecraft:leave_game":1,"minecraft:time_since_death":32675,"minecraft:time_since_rest":32704,"minecraft:sprint_one_cm":80807,"minecraft:damage_taken":604,"minecraft:walk_one_cm":51018,"minecraft:damage_blocked_by_shield":390,"minecraft:drop":13,"minecraft:damage_dealt":1388,"minecraft:swim_one_cm":1796,"minecraft:fly_one_cm":105573,"minecraft:crouch_one_cm":25698,"minecraft:play_time":37416,"minecraft:deaths":1,"minecraft:sneak_time":9460,"minecraft:walk_under_water_one_cm":3948,"minecraft:boat_one_cm":2009,"minecraft:jump":683,"minecraft:walk_on_water_one_cm":5251,"minecraft:total_world_time":37416,"minecraft:fall_one_cm":27294},"minecraft:picked_up":{"minecraft:crafting_table":6,"minecraft:oak_log":11,"minecraft:amethyst_block":6,"minecraft:string":1,"minecraft:lapis_lazuli":62,"minecraft:dirt":8,"minecraft:bone":4,"minecraft:wheat_seeds":1,"minecraft:cobbled_deepslate":46,"minecraft:raw_gold":19,"minecraft:iron_ingot":1,"minecraft:oak_boat":1,"minecraft:calcite":39,"minecraft:furnace":6,"minecraft:raw_iron":60,"minecraft:torch":1,"minecraft:dripstone_block":15,"minecraft:porkchop":5,"minecraft:amethyst_shard":10,"minecraft:pointed_dripstone":22,"minecraft:spider_eye":1,"minecraft:arrow":2,"minecraft:diamond":22,"minecraft:hay_block":4,"minecraft:coal":48,"minecraft:cobblestone":88},"minecraft:used":{"minecraft:water_bucket":20,"minecraft:stone_sword":4,"minecraft:stone_pickaxe":62,"minecraft:shield":7,"minecraft:wooden_pickaxe":59,"minecraft:iron_sword":16,"minecraft:iron_chestplate":1,"minecraft:torch":14,"minecraft:dirt":8,"minecraft:crafting_table":7,"minecraft:lava_bucket":1,"minecraft:iron_axe":2,"minecraft:bread":6,"minecraft:iron_pickaxe":249,"minecraft:iron_helmet":1,"minecraft:iron_boots":1,"minecraft:stone_axe":4,"minecraft:cobblestone":25,"minecraft:furnace":10,"minecraft:bucket":22,"minecraft:oak_boat":1,"minecraft:cobbled_deepslate":31,"minecraft:iron_leggings":1},"minecraft:dropped":{"minecraft:stone_axe":1,"minecraft:wheat_seeds":1,"minecraft:stone_sword":1,"minecraft:stone_shovel":1,"minecraft:pointed_dripstone":4,"minecraft:arrow":2,"minecraft:stone_pickaxe":1,"minecraft:bone":4},"minecraft:broken":{"minecraft:iron_pickaxe":1,"minecraft:wooden_pickaxe":1},"minecraft:killed":{"minecraft:pig":2,"minecraft:spider":3,"minecraft:skeleton":3},"minecraft:killed_by":{"minecraft:player":1},"minecraft:crafted":{"minecraft:oak_planks":44,"minecraft:stone_shovel":1,"minecraft:cooked_porkchop":5,"minecraft:crafting_table":1,"minecraft:wooden_pickaxe":1,"minecraft:iron_helmet":1,"minecraft:iron_sword":1,"minecraft:furnace":4,"minecraft:bucket":1,"minecraft:stone_axe":1,"minecraft:bread":12,"minecraft:air":0,"minecraft:oak_boat":1,"minecraft:iron_boots":1,"minecraft:iron_chestplate":1,"minecraft:shield":1,"minecraft:iron_axe":1,"minecraft:stick":32,"minecraft:iron_ingot":36,"minecraft:iron_pickaxe":1,"minecraft:stone_pickaxe":1,"minecraft:stone_sword":1,"minecraft:iron_shovel":1,"minecraft:iron_leggings":1,"minecraft:torch":28,"minecraft:wheat":36},"minecraft:mined":{"minecraft:diamond_ore":2,"minecraft:large_amethyst_bud":1,"minecraft:deepslate_diamond_ore":20,"minecraft:amethyst_cluster":1,"minecraft:crafting_table":6,"minecraft:short_grass":11,"minecraft:budding_amethyst":8,"minecraft:grass_block":2,"minecraft:calcite":39,"minecraft:cobblestone":16,"minecraft:lapis_ore":3,"minecraft:deepslate_gold_ore":14,"minecraft:amethyst_block":6,"minecraft:furnace":6,"minecraft:iron_ore":20,"minecraft:cobbled_deepslate":20,"minecraft:deepslate_lapis_ore":6,"minecraft:coal_ore":48,"minecraft:pointed_dripstone":3,"minecraft:oak_log":11,"minecraft:deepslate_iron_ore":40,"minecraft:dirt":6,"minecraft:dripstone_block":11,"minecraft:stone":72,"minecraft:gold_ore":5,"minecraft:deepslate":28}},"DataVersion":3953}